[
  {
    "title": "Абһа",
    "value": "даңқ, Баһа сөзінің күшейтпелі түрі, glory"
  },
  {
    "title": "Адалдық шыңы",
    "value": "феникс құсы мекендеген жер mount of faithfulness(phoenix)"
  },
  {
    "title": "Айып",
    "value": "кемшілік, fault"
  },
  {
    "title": "Аңқа құсы",
    "value": "Қап тауын мекен еткен аңыздағы құс"
  },
  {
    "title": "Асыл",
    "value": "жасырын, тылсым hidden"
  },
  {
    "title": "Ашкөз",
    "value": "хасис (азер.) – бергісі келмейді; харис, херс – анағұрлым көбірек алғанды қалайды"
  },
  {
    "title": "Аяғына таяды",
    "value": "аяқталды, бітті ended"
  },
  {
    "title": "Әуен",
    "value": "күй, әуез melody"
  },
  {
    "title": "Әшекейлеу",
    "value": "безендіру, әрлеу adorn"
  },
  {
    "title": "Бағалау",
    "value": "қымбат нәрсе ретінде сақтау, ерекше қарау treasure"
  },
  {
    "title": "Бақи",
    "value": "мәңгі, мәңгі өлмейтін, өшпес"
  },
  {
    "title": "Барлық жағдайда",
    "value": "қандайда жағдай болмасын ever"
  },
  {
    "title": "Баян",
    "value": "сөз, utterance"
  },
  {
    "title": "Безу",
    "value": "бас тарту, қашу, жақындамау shun"
  },
  {
    "title": "Биігі",
    "value": "бұл жерде шыңы, дәрежесі height"
  },
  {
    "title": "Бәйтерек",
    "value": "ағаш, аңыздағы самұрық құсы мекендеген алып ағаш"
  },
  {
    "title": "Бұлақ",
    "value": "ағыс stream"
  },
  {
    "title": "Бүлікшілер",
    "value": "дүрбелең тудырушылар, көтерілісшілер, қарсыласушылар rebellious"
  },
  {
    "title": "Гүлбақ",
    "value": "гүлстан, гүлдер мекені, гүлдер өсетін бақ rose garden цветник"
  },
  {
    "title": "Ғапіл - (азер. гофиль) немқұрайлы, careless, sleeping, negligent ғапілдік",
    "value": "(азер. гофиль) немқұрайлы, careless, sleeping, negligent ғапілдік - немқұрайлылық heedlessness, (азер. жоһиль – ignorant, illiterate)"
  },
  {
    "title": "Ғашықтық",
    "value": "махаббат (өзб.ишқ) love"
  },
  {
    "title": "Ғибрат",
    "value": "мысал, үлгі"
  },
  {
    "title": "Даңқымның мөрімен мөрлеу",
    "value": "даңқыммен мөрлеу"
  },
  {
    "title": "Данышпан",
    "value": "дана, данагөй, оқымысты learned"
  },
  {
    "title": "Дидар",
    "value": "келбет, жүз countenance"
  },
  {
    "title": "Дидарласу",
    "value": "кездесу, жолығу, тілдесу"
  },
  {
    "title": "Дос тұту",
    "value": "дос қылу, дос ету, достасу make friend"
  },
  {
    "title": "Есу",
    "value": "желдің есуі waft"
  },
  {
    "title": "Жақындасу",
    "value": "шын достасу"
  },
  {
    "title": "Жамал",
    "value": "сұлулық, әсемдік"
  },
  {
    "title": "Жар",
    "value": "Сүйікті, Дос"
  },
  {
    "title": "Жарылқаған",
    "value": "ақ баталы, батаға кенелген, Құдай жарылқаған blessed"
  },
  {
    "title": "Жұрдай",
    "value": "құр бос, бос void, empty"
  },
  {
    "title": "Зейнет",
    "value": "әшекей adorning"
  },
  {
    "title": "Зұлмат",
    "value": "қараңғылық, қапас, түнек darkness"
  },
  {
    "title": "Игі істер",
    "value": "сауаптар"
  },
  {
    "title": "Иззат",
    "value": "ізет, даңқ, glory"
  },
  {
    "title": "Имансыз",
    "value": "құдайсыз, Құдайдан безген, Құдайға сенбейтін, Құдайдан қорықпайтын адам ungodly"
  },
  {
    "title": "Киелі",
    "value": "қасиетті мұқаддас"
  },
  {
    "title": "Қақпа",
    "value": "дарбаза, есік gate"
  },
  {
    "title": "Қапас",
    "value": "тор, cage"
  },
  {
    "title": "Қасиеттілік",
    "value": "киелілік sanctity"
  },
  {
    "title": "Қауым",
    "value": "мекендеуші, тұрғын dweller"
  },
  {
    "title": "Қосын",
    "value": "сарбаз, жасақ, әскер, concourse"
  },
  {
    "title": "Қош тұту",
    "value": "қош көру, артық көру, артық санау, қалау prefer"
  },
  {
    "title": "Құмай құсы",
    "value": "сиқырлы көрегендік феникс құсы, бақыт құсы. Ол кімге өзінің көлеңкесін түсірсе, сол адамды патша етеді деп есептелген."
  },
  {
    "title": "Қымбат",
    "value": "бағалы, теңдессіз, асыл precious"
  },
  {
    "title": "Қырмызы",
    "value": "қызылдың бір реңкі"
  },
  {
    "title": "Лағынет",
    "value": "қарғыс ату, accurse"
  },
  {
    "title": "Мейірімділік",
    "value": "(азер. лютф) kindness"
  },
  {
    "title": "Мекендеу",
    "value": "бір жерде өмір сүру, тұру, паналау dwell"
  },
  {
    "title": "Мекенсіздік",
    "value": "ғайыптық, басы да, аяғы да жоқ жер, placeless, (азер. ломачон), Құдай"
  },
  {
    "title": "Мемлекет",
    "value": "ел, патшалық, орда realm"
  },
  {
    "title": "Мехнат",
    "value": "арабша еңбек сөзі"
  },
  {
    "title": "Мүбәрак",
    "value": "киелі, hallowed"
  },
  {
    "title": "Налу",
    "value": "назалану, қамығу, қапалану bewail"
  },
  {
    "title": "Насихат",
    "value": "кеңес, advice"
  },
  {
    "title": "Нәпсі",
    "value": "құмарлық desire, self"
  },
  {
    "title": "Несібе",
    "value": "үлес, portion"
  },
  {
    "title": "Өсиет",
    "value": "аһд Covenant"
  },
  {
    "title": "Пана",
    "value": "баспана, үй shelter, abode"
  },
  {
    "title": "Пана іздеу",
    "value": "мекендеу abide"
  },
  {
    "title": "Перде",
    "value": "бүркеніш veil"
  },
  {
    "title": "Пердесіз",
    "value": "бүркеусіз, хиджабсыз veilless"
  },
  {
    "title": "Разылық",
    "value": "pleasure"
  },
  {
    "title": "Рақат төсегі",
    "value": "құр бекер жату, ештеңе істемеу, рақаттанып жату bed of ease"
  },
  {
    "title": "Рақымды",
    "value": "қайырымды, мейірімді merciful"
  },
  {
    "title": "Ризалық",
    "value": "ерік will"
  },
  {
    "title": "Ризашылық",
    "value": "good pleasure"
  },
  {
    "title": "Ризван",
    "value": "жәннат бағы"
  },
  {
    "title": "Сәжде ету",
    "value": "бас ию, prostrate"
  },
  {
    "title": "Сүйкімділік",
    "value": "әсерлік, әсемділік charm"
  },
  {
    "title": "Сүйікті",
    "value": "басқаша жар, дос"
  },
  {
    "title": "Сүйініш",
    "value": "қуаныш, шаттық joy"
  },
  {
    "title": "Сүлейменнің жаршысы",
    "value": "оның сүйіктісіне хат тасыған бәбісек құсы"
  },
  {
    "title": "Сый",
    "value": "favor, grace"
  },
  {
    "title": "Талассыз",
    "value": "айқын irrevocably"
  },
  {
    "title": "Тақуа",
    "value": "тура жолдағы адам, құдайшыл, праведный, righteous"
  },
  {
    "title": "Тас тақта",
    "value": "шарғы tablet"
  },
  {
    "title": "Тауап ету",
    "value": "айналып жүру circle round"
  },
  {
    "title": "Тәңірі",
    "value": "Құдай, Жаратушы, Билеуші Ие (Lord)"
  },
  {
    "title": "Тәрк ету",
    "value": "теріс айналу, бас тарту"
  },
  {
    "title": "Тостаған",
    "value": "кесе, пиала cup"
  },
  {
    "title": "Толық жойылу",
    "value": "құру, жоқ болу, құрдымға кету utter loss"
  },
  {
    "title": "Шақыру",
    "value": "уаһи, аян (call)"
  },
  {
    "title": "Уәжіп",
    "value": "міндетті түрде орындау, binding"
  },
  {
    "title": "Ұланның шырайы",
    "value": "Жігіттің, Жастың сымбаттылығы, сұлулығы"
  },
  {
    "title": "Үлпәт",
    "value": "бауыр басу, байлану привязанность affection"
  },
  {
    "title": "Үміт үзу",
    "value": "сенім артпау, сенімін жоғалу put no trust"
  },
  {
    "title": "Хақы",
    "value": "құқы, claim"
  },
  {
    "title": "Хикмет",
    "value": "даналық wisdom"
  },
  {
    "title": "Хикметтердің",
    "value": "даналықтар wisdoms"
  },
  {
    "title": "Хикмет иелері",
    "value": "даналар, данышпан, данагөй адамдар wise"
  },
  {
    "title": "Шағылу",
    "value": "Күн көзі айна бетінде шағылады, көріну, бейнесі түсу reflection"
  },
  {
    "title": "Шеба (Саба)",
    "value": "Шеба патшайымы мекен еткен жер, Сүлеймен патша сүйген патшайымның елі; қазіргі Йемен еліндегі қала."
  },
  {
    "title": "Шеңбер",
    "value": "атырап precincts"
  },
  {
    "title": "Ширк",
    "value": "екі нәрсені тең қылу, бұл жерде Құдайға серік қосу: Құдай жалғыз емес, Оның жанында басқа да күштер бар misbelief"
  },
  {
    "title": "Шырай",
    "value": "жамал, әсемдік, сұлулық"
  },
  {
    "title": "Ынсап",
    "value": "әділдік, әділеттік justice"
  },
  {
    "title": "Ықтияр ету",
    "value": "таңдау choose"
  },
  {
    "title": "Іздеу",
    "value": "талпыну, асығу seek"
  },
  {
    "title": "Ізет",
    "value": "даңқ glory"
  }
]